units/top/rtl/counter_4bit.sv
module counter_4bit (input wire clk, input wire reset, output reg [3:0] count);

  always_ff @(posedge clk or posedge reset) begin
      if (reset) begin
          count <= 4'b0000;
      end else begin
          count <= count + 1;
      end
  end

endmodule

units/top/testbench/tb_counter_4bit.sv
`timescale 1ns/1ps

module tb_counter_4bit;

    // Testbench signals
    reg        clk;
    reg        reset;
    wire [3:0] count;

    // DUT instantiation
    counter_4bit dut (
        .clk   (clk),
        .reset (reset),
        .count (count)
    );

    // Clock generation: 100 MHz (10 ns period)
    initial begin
        clk = 1'b0;
        forever #5 clk = ~clk;   // toggle every 5 ns → period = 10 ns
    end

    // Stimulus
    initial begin
        // VCD dump for GTKWave
        $dumpfile("counter_4bit_tb.vcd");
        $dumpvars(0, tb_counter_4bit);

        // Initial state
        reset = 1'b1;   // assert reset
        #20;            // hold reset for 20 ns

        reset = 1'b0;   // release reset, counter should start incrementing

        #200;           // let it count for a while

        // Pulse reset again to see it go back to 0
        reset = 1'b1;
        #20;
        reset = 1'b0;

        #200;           // more counting

        $finish;
    end

endmodule

units/top/sim/sim/counter_4bit_tb.vcd
$date
	Sun Nov 30 19:49:11 2025
$end
$version
	Icarus Verilog
$end
$timescale
	1ps
$end
$scope module tb_counter_4bit $end
$var wire 4 ! count [3:0] $end
$var reg 1 " clk $end
$var reg 1 # reset $end
$scope module dut $end
$var wire 1 " clk $end
$var wire 1 # reset $end
$var reg 4 $ count [3:0] $end
$upscope $end
$upscope $end
$enddefinitions $end
$comment Show the parameter values. $end
$dumpall
$end
#0
$dumpvars
b0 $
1#
0"
b0 !
$end
#5000
1"
#10000
0"
#15000
1"
#20000
0"
0#
#25000
b1 !
b1 $
1"
#30000
0"
#35000
b10 !
b10 $
1"
#40000
0"
#45000
b11 !
b11 $
1"
#50000
0"
#55000
b100 !
b100 $
1"
#60000
0"
#65000
b101 !
b101 $
1"
#70000
0"
#75000
b110 !
b110 $
1"
#80000
0"
#85000
b111 !
b111 $
1"
#90000
0"
#95000
b1000 !
b1000 $
1"
#100000
0"
#105000
b1001 !
b1001 $
1"
#110000
0"
#115000
b1010 !
b1010 $
1"
#120000
0"
#125000
b1011 !
b1011 $
1"
#130000
0"
#135000
b1100 !
b1100 $
1"
#140000
0"
#145000
b1101 !
b1101 $
1"
#150000
0"
#155000
b1110 !
b1110 $
1"
#160000
0"
#165000
b1111 !
b1111 $
1"
#170000
0"
#175000
b0 !
b0 $
1"
#180000
0"
#185000
b1 !
b1 $
1"
#190000
0"
#195000
b10 !
b10 $
1"
#200000
0"
#205000
b11 !
b11 $
1"
#210000
0"
#215000
b100 !
b100 $
1"
#220000
b0 !
b0 $
0"
1#
#225000
1"
#230000
0"
#235000
1"
#240000
0"
0#
#245000
b1 !
b1 $
1"
#250000
0"
#255000
b10 !
b10 $
1"
#260000
0"
#265000
b11 !
b11 $
1"
#270000
0"
#275000
b100 !
b100 $
1"
#280000
0"
#285000
b101 !
b101 $
1"
#290000
0"
#295000
b110 !
b110 $
1"
#300000
0"
#305000
b111 !
b111 $
1"
#310000
0"
#315000
b1000 !
b1000 $
1"
#320000
0"
#325000
b1001 !
b1001 $
1"
#330000
0"
#335000
b1010 !
b1010 $
1"
#340000
0"
#345000
b1011 !
b1011 $
1"
#350000
0"
#355000
b1100 !
b1100 $
1"
#360000
0"
#365000
b1101 !
b1101 $
1"
#370000
0"
#375000
b1110 !
b1110 $
1"
#380000
0"
#385000
b1111 !
b1111 $
1"
#390000
0"
#395000
b0 !
b0 $
1"
#400000
0"
#405000
b1 !
b1 $
1"
#410000
0"
#415000
b10 !
b10 $
1"
#420000
0"
#425000
b11 !
b11 $
1"
#430000
0"
#435000
b100 !
b100 $
1"
