openlane_flow/designs/param_counter/src/param_counter.sv
/* 
Write a parameterized counter module:
Parameters: WIDTH, DOWN (0 = up, 1 = down), SATURATE (0 = wrap, 1 = saturating)
Ports: clk, rst_n, en, load, load_val[WIDTH-1:0], count[WIDTH-1:0]
Behavior:
    On load=1, load load_val
    Else if en=1, increment/decrement depending on DOWN
    If SATURATE=1, stay at max/min instead of wrapping

Constraints:
    Single always_ff block (if using SV)
    No latches, no multiple drivers
    Reset is async or sync – you choose, but be consistent

Deep dive:
    Sketch what synthesis will generate for:
    SATURATE=0 vs SATURATE=1
    DOWN=0 vs DOWN=1
*/

module param_counter #(
    parameter int WIDTH     = 4,
    parameter int DOWN      = 0,
    parameter int SATURATE  = 0
) (
    input  logic                 clk,
    input  logic                 rst_n,
    input  logic                 en,
    input  logic                 load,
    input  logic [WIDTH-1:0]     load_value,
    output logic [WIDTH-1:0]     count
);

    localparam logic [WIDTH-1:0] MAX_VAL = {WIDTH{1'b1}};
    localparam logic [WIDTH-1:0] MIN_VAL = '0;

    always_ff @(posedge clk or negedge rst_n) begin : counter_logic
        if (!rst_n) begin
            count <= '0;                            // ASYNC RESET
        end else begin
            if (load) begin
                count <= load_value;
            end
            else if (en) begin
                if (!DOWN) begin
                    if (SATURATE && count == MAX_VAL) begin
                        count <= MAX_VAL;          // stay at max
                    end
                    else begin
                        count <= count + 1'b1;     // natural wrap if SATURATE==0
                    end
                end
                else begin
                    if (SATURATE && count == MIN_VAL) begin
                        count <= MIN_VAL;          // stay at 0
                    end
                    else begin
                        count <= count - 1'b1;     // natural wrap if SATURATE==0
                    end
                end
            end
        end
    end

endmodule

openlane_flow/designs/param_counter/tb_top/param_counter_tb.sv
`timescale 1ns/1ps

module param_counter_tb;

  reg clk;
  reg rst_n;
  reg en;
  reg load;
  reg [3:0] load_value;
  wire [3:0] count;

  // Instantiate the DUT
  param_counter #(
    .WIDTH(4),
    .DOWN(0),
    .SATURATE(1)
  ) dut (
    .clk        (clk),
    .rst_n      (rst_n),
    .en         (en),
    .load       (load),
    .load_value (load_value),
    .count      (count)
  );

  // Clock generation: 50 MHz
  initial begin
    clk = 0;
    forever #10 clk = ~clk; // 20 ns period
  end

  //stimulus
  initial begin
    // VCD dump for waveform viewing
    $dumpfile("param_counter_tb.vcd");
    $dumpvars(0, param_counter_tb);
    // Initialize signals
    rst_n = 1'b0;
    en = 1'b0;
    load = 1'b0;
    load_value = 4'd0;

    #25;
    rst_n = 1'b1; // Release reset
    
    #20;
    en = 1'b1; // Enable counting

    #200;
    load = 1'b1; // Load new value
    load_value = 4'd10;

    #20;
    load = 1'b0; // Stop loading
    #200;
    en = 1'b0; // Disable counting
    #50;
    $finish;
  end

endmodule

openlane_flow/designs/param_counter/sim/sim/param_counter_tb.vcd
$date
	Sun Dec  7 19:56:54 2025
$end
$version
	Icarus Verilog
$end
$timescale
	1ps
$end
$scope module param_counter_tb $end
$var wire 4 ! count [3:0] $end
$var reg 1 " clk $end
$var reg 1 # en $end
$var reg 1 $ load $end
$var reg 4 % load_value [3:0] $end
$var reg 1 & rst_n $end
$scope module dut $end
$var wire 1 " clk $end
$var wire 1 # en $end
$var wire 1 $ load $end
$var wire 4 ' load_value [3:0] $end
$var wire 1 & rst_n $end
$var parameter 32 ( DOWN $end
$var parameter 4 ) MAX_VAL $end
$var parameter 4 * MIN_VAL $end
$var parameter 32 + SATURATE $end
$var parameter 32 , WIDTH $end
$var reg 4 - count [3:0] $end
$scope begin counter_logic $end
$upscope $end
$upscope $end
$upscope $end
$enddefinitions $end
$comment Show the parameter values. $end
$dumpall
b100 ,
b1 +
b0 *
b1111 )
b0 (
$end
#0
$dumpvars
b0 -
b0 '
0&
b0 %
0$
0#
0"
b0 !
$end
#10000
1"
#20000
0"
#25000
1&
#30000
1"
#40000
0"
#45000
1#
#50000
b1 !
b1 -
1"
#60000
0"
#70000
b10 !
b10 -
1"
#80000
0"
#90000
b11 !
b11 -
1"
#100000
0"
#110000
b100 !
b100 -
1"
#120000
0"
#130000
b101 !
b101 -
1"
#140000
0"
#150000
b110 !
b110 -
1"
#160000
0"
#170000
b111 !
b111 -
1"
#180000
0"
#190000
b1000 !
b1000 -
1"
#200000
0"
#210000
b1001 !
b1001 -
1"
#220000
0"
#230000
b1010 !
b1010 -
1"
#240000
0"
#245000
b1010 %
b1010 '
1$
#250000
1"
#260000
0"
#265000
0$
#270000
b1011 !
b1011 -
1"
#280000
0"
#290000
b1100 !
b1100 -
1"
#300000
0"
#310000
b1101 !
b1101 -
1"
#320000
0"
#330000
b1110 !
b1110 -
1"
#340000
0"
#350000
b1111 !
b1111 -
1"
#360000
0"
#370000
1"
#380000
0"
#390000
1"
#400000
0"
#410000
1"
#420000
0"
#430000
1"
#440000
0"
#450000
1"
#460000
0"
#465000
0#
